Metadata-Version: 2.1
Name: rflow-tfx
Version: 1.1.18
Summary: TensorFlow Extended (TFX) is README.ml-pipelines-sdk.md TensorFlow-based general-purpose machine learning platform implemented at Google.
Home-page: https://www.tensorflow.org/tfx
Author: Google LLC
Author-email: tensorflow-extended-dev@googlegroups.com
License: Apache 2.0
Download-URL: https://github.com/tensorflow/tfx/tags
Keywords: tensorflow tfx
Platform: UNKNOWN
Classifier: Development Status :: 4 - Beta
Classifier: Intended Audience :: Developers
Classifier: Intended Audience :: Education
Classifier: Intended Audience :: Science/Research
Classifier: License :: OSI Approved :: Apache Software License
Classifier: Operating System :: OS Independent
Classifier: Programming Language :: Python
Classifier: Programming Language :: Python :: 3
Classifier: Programming Language :: Python :: 3.6
Classifier: Programming Language :: Python :: 3.7
Classifier: Programming Language :: Python :: 3.8
Classifier: Programming Language :: Python :: 3 :: Only
Classifier: Topic :: Scientific/Engineering
Classifier: Topic :: Scientific/Engineering :: Artificial Intelligence
Classifier: Topic :: Scientific/Engineering :: Mathematics
Classifier: Topic :: Software Development
Classifier: Topic :: Software Development :: Libraries
Classifier: Topic :: Software Development :: Libraries :: Python Modules
Requires-Python: >=3.6,<3.9
Requires-Dist: rflow-ml-pipelines-sdk (==1.1.18)
Requires-Dist: absl-py (<0.11,>=0.9)
Requires-Dist: ml-metadata (<0.29,>=0.28)
Requires-Dist: protobuf (<4,>=3.12.2)
Requires-Dist: six (<2,>=1)
Requires-Dist: docker (<5,>=4.1)
Requires-Dist: jinja2 (<3,>=2.7.3)
Requires-Dist: apache-beam[gcp] (==2.39.0)
Requires-Dist: attrs (<21,>=19.3.0)
Requires-Dist: click (<8,>=7)
Requires-Dist: google-api-python-client (<2,>=1.7.8)
Requires-Dist: grpcio (<2,>=1.28.1)
Requires-Dist: httplib2 (<0.20)
Requires-Dist: pyparsing (<3.0.0a0,>=2.4.2)
Requires-Dist: keras-tuner (<1.0.2,>=1)
Requires-Dist: kubernetes (<12,>=10.0.1)
Requires-Dist: numpy (<1.20,>=1.16)
Requires-Dist: pyarrow (<3,>=1)
Requires-Dist: pyyaml (<6,>=3.12)
Requires-Dist: tensorflow (==2.4.0)
Requires-Dist: tensorflow-hub (<0.10,>=0.9.0)
Requires-Dist: tensorflow-cloud (<0.2,>=0.1)
Requires-Dist: tensorflow-data-validation (<0.29,>=0.28)
Requires-Dist: tensorflow-model-analysis (<0.29,>=0.28)
Requires-Dist: tensorflow-serving-api (!=2.0.*,!=2.1.*,!=2.2.*,!=2.3.*,<3,>=1.15)
Requires-Dist: tensorflow-transform (<0.29,>=0.28)
Requires-Dist: tfx-bsl (<0.29,>=0.28.1)
Provides-Extra: all
Requires-Dist: cattrs (==1.0.0) ; extra == 'all'
Requires-Dist: kfp (<2,>=1.1.0) ; extra == 'all'
Requires-Dist: kfp-pipeline-spec (<0.2,>=0.1.6) ; extra == 'all'
Requires-Dist: pytest (<6,>=5) ; extra == 'all'
Requires-Dist: werkzeug (==0.16.1) ; extra == 'all'
Requires-Dist: tensorflowjs (<3,>=2.0.1.post1) ; extra == 'all'
Requires-Dist: presto-python-client (<0.8,>=0.7) ; extra == 'all'
Requires-Dist: slackclient (<3,>=2.8.2) ; extra == 'all'
Requires-Dist: websocket-client (<1,>=0.57) ; extra == 'all'
Requires-Dist: tensorflow-text (<3,>=1.15.1) ; extra == 'all'
Requires-Dist: flatbuffers (<2,>=1.12) ; extra == 'all'
Requires-Dist: tflite-support (<0.1.1,>=0.1.0a1) ; extra == 'all'
Requires-Dist: tensorflow-ranking (<0.4,>=0.3.3) ; extra == 'all'
Requires-Dist: struct2tensor (<0.29,>=0.28) ; extra == 'all'
Requires-Dist: apache-airflow[mysql] (<2,>=1.10.10) ; (python_version != "3.7" or platform_system != "Darwin") and extra == 'all'
Requires-Dist: apache-airflow[mysql] (<1.10.14,>=1.10.10) ; (python_version == "3.7" and platform_system == "Darwin") and extra == 'all'
Provides-Extra: docker-image
Requires-Dist: kfp-pipeline-spec (<0.2,>=0.1.6) ; extra == 'docker-image'
Requires-Dist: mmh (<3,>=2.2) ; extra == 'docker-image'
Requires-Dist: python-snappy (<0.6,>=0.5) ; extra == 'docker-image'
Provides-Extra: examples
Requires-Dist: presto-python-client (<0.8,>=0.7) ; extra == 'examples'
Requires-Dist: slackclient (<3,>=2.8.2) ; extra == 'examples'
Requires-Dist: websocket-client (<1,>=0.57) ; extra == 'examples'
Requires-Dist: tensorflow-text (<3,>=1.15.1) ; extra == 'examples'
Requires-Dist: flatbuffers (<2,>=1.12) ; extra == 'examples'
Requires-Dist: tflite-support (<0.1.1,>=0.1.0a1) ; extra == 'examples'
Requires-Dist: tensorflow-ranking (<0.4,>=0.3.3) ; extra == 'examples'
Requires-Dist: struct2tensor (<0.29,>=0.28) ; extra == 'examples'
Provides-Extra: test
Requires-Dist: cattrs (==1.0.0) ; extra == 'test'
Requires-Dist: kfp (<2,>=1.1.0) ; extra == 'test'
Requires-Dist: kfp-pipeline-spec (<0.2,>=0.1.6) ; extra == 'test'
Requires-Dist: pytest (<6,>=5) ; extra == 'test'
Requires-Dist: werkzeug (==0.16.1) ; extra == 'test'
Requires-Dist: apache-airflow[mysql] (<2,>=1.10.10) ; (python_version != "3.7" or platform_system != "Darwin") and extra == 'test'
Requires-Dist: apache-airflow[mysql] (<1.10.14,>=1.10.10) ; (python_version == "3.7" and platform_system == "Darwin") and extra == 'test'
Provides-Extra: tfjs
Requires-Dist: tensorflowjs (<3,>=2.0.1.post1) ; extra == 'tfjs'
